msdrive/__init__.py
msdrive/constants.py
msdrive/drive.py
msdrive/exceptions.py
msdrive/onedrive.py
msdrive/sharepoint.py
onedrive_sharepoint_python_sdk-0.0.2.dist-info/LICENSE.txt
onedrive_sharepoint_python_sdk-0.0.2.dist-info/METADATA
onedrive_sharepoint_python_sdk-0.0.2.dist-info/WHEEL
onedrive_sharepoint_python_sdk-0.0.2.dist-info/top_level.txt
onedrive_sharepoint_python_sdk-0.0.2.dist-info/RECORD
