Metadata-Version: 2.1
Name: onedrive-sharepoint-python-sdk
Version: 0.0.2
Summary: A Python SDK for accessing files in OneDrive & SharePoint using the Microsoft Graph API
Author-email: Jason M <emailfire@gmail.com>
License: MIT License        
Project-URL: Homepage, https://github.com/fire015/onedrive-sharepoint-python-sdk
Project-URL: Bug Tracker, https://github.com/fire015/onedrive-sharepoint-python-sdk/issues
Keywords: onedrive,sharepoint,microsoft
Classifier: Programming Language :: Python :: 3.7
Classifier: Programming Language :: Python :: 3.8
Classifier: Programming Language :: Python :: 3.9
Classifier: Programming Language :: Python :: 3.10
Classifier: License :: OSI Approved :: MIT License
Requires-Python: >=3.7
License-File: LICENSE.txt
Requires-Dist: requests
Provides-Extra: tests
Requires-Dist: pytest ; extra == 'tests'
Requires-Dist: requests-mock ; extra == 'tests'
